pandoc_mermaid_selenium_filter/__init__.py
pandoc_mermaid_selenium_filter/filter.py
pandoc_mermaid_selenium_filter/mermaid_converter.py
pandoc_mermaid_selenium_filter/static/__init__.py
pandoc_mermaid_selenium_filter/static/npm/__init__.py
pandoc_mermaid_selenium_filter/static/templates/__init__.py
pandoc_mermaid_selenium_filter/static/templates/mermaid.html
pandoc_mermaid_selenium_filter/static/templates/__init__.py
pandoc_mermaid_selenium_filter/static/templates/mermaid.html
pandoc_mermaid_selenium_filter/static/npm/@iconify-json/logos/icons.json
pandoc_mermaid_selenium_filter/static/npm/@iconify-json/mdi/icons.json
pandoc_mermaid_selenium_filter/static/npm/mermaid/dist/mermaid.min.js
pandoc_mermaid_selenium_filter-1.0.1.dist-info/METADATA
pandoc_mermaid_selenium_filter-1.0.1.dist-info/WHEEL
pandoc_mermaid_selenium_filter-1.0.1.dist-info/entry_points.txt
pandoc_mermaid_selenium_filter-1.0.1.dist-info/licenses/LICENSE
pandoc_mermaid_selenium_filter-1.0.1.dist-info/RECORD
