Metadata-Version: 2.4
Name: pandoc-mermaid-selenium-filter
Version: 1.0.1
Summary: A Pandoc filter that converts Mermaid code blocks to images using Selenium
Project-URL: Homepage, https://github.com/itTkm/pandoc-mermaid-selenium-filter
Project-URL: Repository, https://github.com/itTkm/pandoc-mermaid-selenium-filter.git
Project-URL: Issues, https://github.com/itTkm/pandoc-mermaid-selenium-filter/issues
Author: itTkm
License-Expression: MIT
License-File: LICENSE
Keywords: filter,markdown,mermaid,pandoc,selenium
Classifier: Development Status :: 5 - Production/Stable
Classifier: Environment :: Console
Classifier: Intended Audience :: Developers
Classifier: Intended Audience :: Science/Research
Classifier: License :: OSI Approved :: MIT License
Classifier: Programming Language :: Python :: 3
Classifier: Programming Language :: Python :: 3.13
Classifier: Topic :: Documentation
Classifier: Topic :: Text Processing :: Markup :: Markdown
Requires-Python: >=3.9
Requires-Dist: pandocfilters>=1.5.1
Requires-Dist: selenium>=4.27.1
Requires-Dist: webdriver-manager>=4.0.2
Provides-Extra: dev
Requires-Dist: pytest-cov>=6.0.0; extra == 'dev'
Requires-Dist: pytest>=8.3.4; extra == 'dev'
